climate/__init__.py
climate/cli.json
climate/climate.py
climate/core/__init__.py
climate/core/help.py
climate/core/menu.py
climate/core/parsing.py
climate/core/settings.py
climate/core/tests/__init__.py
climate/lib/__init__.py
climate/lib/actions.py
climate/lib/converters.py
climate/lib/data.py
climate/lib/inquirers.py
climate/lib/mapper.py
climate/lib/utilities.py
climate/lib/tests/__init__.py
climate/lib/tests/test_converters.py
climate/lib/tests/test_utilities.py
climate/lib/tests/data/test_cli.json
climate/lib/tests/data/test_commands.json
climate/lib/tests/data/test_general.json
climate/lib/tests/data/test_write.json
py_CliMate-0.1.0.dist-info/LICENSE
py_CliMate-0.1.0.dist-info/METADATA
py_CliMate-0.1.0.dist-info/WHEEL
py_CliMate-0.1.0.dist-info/entry_points.txt
py_CliMate-0.1.0.dist-info/top_level.txt
py_CliMate-0.1.0.dist-info/RECORD
